<KubernetesDeploymentModel>  
  <deployments>        
    <deployments>      
      <name>x</name>
      <replicas>1</replicas>
      <labels>                
        <labels>          
          <key>x</key>
          <value>y</value>
        </labels>
      </labels>
      <container>                
        <container>          
          <name>x</name>
          <image>y</image>
          <containerPorts>                        
            <containerPorts>              
              <name>2</name>
              <port>1</port>
            </containerPorts>
          </containerPorts>
          <environmentVariables>                        
            <environmentVariables>              
              <key>x</key>
              <value>y</value>
            </environmentVariables>
          </environmentVariables>
        </container>
      </container>
    </deployments>
  </deployments>
  <services>        
    <services>      
      <name>x</name>
      <servicePorts>                
        <servicePorts>          
          <name>80</name>
          <port>80</port>
          <targetPort>80</targetPort>
        </servicePorts>
      </servicePorts>
      <selectors>                
        <selectors>          
          <key>x</key>
          <value>y</value>
        </selectors>
      </selectors>
    </services>
  </services>
</KubernetesDeploymentModel>